Metadata-Version: 2.1
Name: distance3d
Version: 0.9.0
Summary: Distance computation and collision detection in 3D.
Home-page: https://github.com/AlexanderFabisch/distance3d
Author: Alexander Fabisch
Author-email: afabisch@googlemail.com
License: BSD-3-Clause
Classifier: Programming Language :: Python :: 3
Classifier: License :: OSI Approved :: BSD License
Classifier: Operating System :: OS Independent
Classifier: Topic :: Scientific/Engineering :: Mathematics
Classifier: Topic :: Scientific/Engineering :: Visualization
Provides-Extra: all
Provides-Extra: test
Provides-Extra: doc
Provides-Extra: benchmark
License-File: LICENSE
